django_boxberry/__init__.py
django_boxberry/admin.py
django_boxberry/admin_filters.py
django_boxberry/apps.py
django_boxberry/client.py
django_boxberry/fields.py
django_boxberry/models.py
django_boxberry/signals.py
django_boxberry/tests.py
django_boxberry/views.py
django_boxberry/fixtures/status.json
django_boxberry/management/__init__.py
django_boxberry/management/commands/__init__.py
django_boxberry/management/commands/update_parsels_statuses.py
django_boxberry/migrations/0001_initial.py
django_boxberry/migrations/0002_auto_20181031_1119.py
django_boxberry/migrations/__init__.py
django_boxberry-0.1.7.dist-info/DESCRIPTION.rst
django_boxberry-0.1.7.dist-info/METADATA
django_boxberry-0.1.7.dist-info/RECORD
django_boxberry-0.1.7.dist-info/WHEEL
django_boxberry-0.1.7.dist-info/metadata.json
django_boxberry-0.1.7.dist-info/top_level.txt
project/__init__.py
project/settings.py
project/urls.py
project/wsgi.py
