Metadata-Version: 2.0
Name: django-boxberry
Version: 0.1.7
Summary: Приложение для интеграции с API Boxberry
Home-page: https://github.com/AlekseevAV/django-boxberry
Author: Aleksandr Alekseev
Author-email: alekseevavx@gmail.com
License: MIT
Keywords: django,boxberry
Platform: UNKNOWN
Requires-Dist: boxberry (==0.1.2)
